river_templates/__init__.py
river_templates/cli.py
river_templates/path_manager/__init__.py
river_templates/path_manager/generate.py
river_templates/path_manager/main.py
river_templates/path_manager/structure.py
river_templates-0.1.0.dist-info/METADATA
river_templates-0.1.0.dist-info/WHEEL
river_templates-0.1.0.dist-info/entry_points.txt
river_templates-0.1.0.dist-info/licenses/LICENSE
river_templates-0.1.0.dist-info/RECORD
