Metadata-Version: 2.4
Name: river_templates
Version: 0.1.0
Summary: personal templates library
Author-email: river <none@none.com>
License-File: LICENSE
Classifier: Development Status :: 3 - Alpha
Classifier: License :: OSI Approved :: Apache Software License
Classifier: Programming Language :: Python :: 3
Classifier: Programming Language :: Python :: 3.9
Classifier: Programming Language :: Python :: 3.10
Classifier: Programming Language :: Python :: 3.11
Classifier: Programming Language :: Python :: 3.12
Classifier: Programming Language :: Python :: 3.13
Requires-Python: >=3.9
Requires-Dist: click>=8.1.8
Requires-Dist: rich>=13.9.4
Requires-Dist: river-print>=0.1.6
